LICENSE
README.md
setup.py
yadirconv/__init__.py
yadirconv/yadirconv.py
yadirconv.egg-info/PKG-INFO
yadirconv.egg-info/SOURCES.txt
yadirconv.egg-info/dependency_links.txt
yadirconv.egg-info/top_level.txt