Metadata-Version: 2.1
Name: yadirconv
Version: 1.0.3
Summary: Получение статистики по конверсиям из Яндекс Директа в разрезе кампаний, таргетингов, ОС, пола и возраста
Home-page: https://vk.com/lubiviy_alexander
Author: Lubiviy Alexander
Author-email: lybiviyalexandr@gmail.com
License: UNKNOWN
Platform: UNKNOWN
License-File: LICENSE
